flexscspace/__init__.py
flexscspace/v0/__init__.py
flexscspace/v0/models.py
flexscspace/v0/scspace.py
flexscspace/v0/utils.py
flexscspace/v1/__init__.py
flexscspace/v1/models.py
flexscspace/v1/scspace.py
flexscspace/v1/utils.py
flexscspace/v2/__init__.py
flexscspace/v2/models.py
flexscspace/v2/scspace.py
flexscspace/v2/utils.py
flexscspace/v3a/__init__.py
flexscspace/v3a/models.py
flexscspace/v3a/scspace.py
flexscspace/v3a/utils.py
flexscspace/v3b/__init__.py
flexscspace/v3b/models.py
flexscspace/v3b/scspace.py
flexscspace/v3b/utils.py
flexscspace/v3c/__init__.py
flexscspace/v3c/models.py
flexscspace/v3c/scspace.py
flexscspace/v3c/utils.py
flexscspace-1.1.0.dist-info/LICENSE
flexscspace-1.1.0.dist-info/METADATA
flexscspace-1.1.0.dist-info/WHEEL
flexscspace-1.1.0.dist-info/top_level.txt
flexscspace-1.1.0.dist-info/RECORD
