Metadata-Version: 2.1
Name: flexscspace
Version: 1.1.0
Summary: The update to SCSpace provides more flexible version options
Home-page: https://github.com/wangmy2025/flexcspace
Author: wangmy2025
Author-email: wangmy2022@gmail.com
Requires-Python: >=3.8
License-File: LICENSE
